carbon2_server/__init__.py
carbon2_server/app.py
carbon2_server/func.py
carbon2_server/__pycache__/__init__.cpython-39.pyc
carbon2_server/__pycache__/app.cpython-39.pyc
carbon2_server/__pycache__/func.cpython-39.pyc
carbon2_server/configs/carbon2.txt
carbon2_server-0.0.1a9.dist-info/LICENSE
carbon2_server-0.0.1a9.dist-info/METADATA
carbon2_server-0.0.1a9.dist-info/WHEEL
carbon2_server-0.0.1a9.dist-info/entry_points.txt
carbon2_server-0.0.1a9.dist-info/top_level.txt
carbon2_server-0.0.1a9.dist-info/RECORD
